online_scheduler/__init__.py
online_scheduler/online_scheduler.py
online_scheduler-1.6.dist-info/METADATA
online_scheduler-1.6.dist-info/WHEEL
online_scheduler-1.6.dist-info/top_level.txt
online_scheduler-1.6.dist-info/RECORD
